code_include/__init__.py
code_include/error_classes.py
code_include/extension.py
code_include/formatter.py
code_include/helper.py
code_include/source_code.py
sphinx_code_include-2.0.0.dist-info/AUTHORS.rst
sphinx_code_include-2.0.0.dist-info/LICENSE
sphinx_code_include-2.0.0.dist-info/METADATA
sphinx_code_include-2.0.0.dist-info/WHEEL
sphinx_code_include-2.0.0.dist-info/top_level.txt
sphinx_code_include-2.0.0.dist-info/RECORD
