Metadata-Version: 2.2
Name: sphinx-code-include
Version: 2.0.0
Summary: Include source code from any Sphinx project using only its import path
Home-page: https://github.com/ColinKennedy/sphinx-code-include
Author: Colin Kennedy
Author-email: colinvfx@gmail.com
License: BSD-2-Clause
Project-URL: Documentation, https://sphinx-code-include.readthedocs.io/
Project-URL: Changelog, https://sphinx-code-include.readthedocs.io/en/latest/changelog.html
Project-URL: Issue Tracker, https://github.com/ColinKennedy/sphinx-code-include/issues
Keywords: Sphinx,code-include,source-code,source code,include
Classifier: Development Status :: 5 - Production/Stable
Classifier: Intended Audience :: Developers
Classifier: License :: OSI Approved :: BSD License
Classifier: Operating System :: Unix
Classifier: Operating System :: POSIX
Classifier: Operating System :: Microsoft :: Windows
Classifier: Programming Language :: Python
Classifier: Programming Language :: Python :: 3
Classifier: Programming Language :: Python :: 3.9
Classifier: Programming Language :: Python :: 3.10
Classifier: Programming Language :: Python :: 3.11
Classifier: Programming Language :: Python :: Implementation :: CPython
Classifier: Programming Language :: Python :: Implementation :: PyPy
Classifier: Topic :: Utilities
Requires-Python: >=3.9
License-File: LICENSE
License-File: AUTHORS.rst
Requires-Dist: beautifulsoup4>=4.8
Requires-Dist: sphinx>=1.3
Dynamic: author
Dynamic: author-email
Dynamic: classifier
Dynamic: description
Dynamic: home-page
Dynamic: keywords
Dynamic: license
Dynamic: project-url
Dynamic: requires-dist
Dynamic: requires-python
Dynamic: summary
